odoo/addons/base_location_code_program_territory/README.rst
odoo/addons/base_location_code_program_territory/__init__.py
odoo/addons/base_location_code_program_territory/__manifest__.py
odoo/addons/base_location_code_program_territory/i18n/es.po
odoo/addons/base_location_code_program_territory/models/__init__.py
odoo/addons/base_location_code_program_territory/models/res_city_zip.py
odoo/addons/base_location_code_program_territory/models/res_partner.py
odoo/addons/base_location_code_program_territory/readme/CONFIGURE.md
odoo/addons/base_location_code_program_territory/readme/CONTRIBUTORS.md
odoo/addons/base_location_code_program_territory/readme/DESCRIPTION.md
odoo/addons/base_location_code_program_territory/readme/INSTALL.md
odoo/addons/base_location_code_program_territory/readme/USAGE.md
odoo/addons/base_location_code_program_territory/static/description/icon.png
odoo/addons/base_location_code_program_territory/static/description/index.html
odoo/addons/base_location_code_program_territory/tests/__init__.py
odoo/addons/base_location_code_program_territory/tests/test_base_location_code_program_territory.py
odoo/addons/base_location_code_program_territory/views/res_city_zip_views.xml
odoo_addon_base_location_code_program_territory-18.0.1.0.0.1.dist-info/METADATA
odoo_addon_base_location_code_program_territory-18.0.1.0.0.1.dist-info/WHEEL
odoo_addon_base_location_code_program_territory-18.0.1.0.0.1.dist-info/top_level.txt
odoo_addon_base_location_code_program_territory-18.0.1.0.0.1.dist-info/RECORD
